{
  "version": 2,
  "projects": {
    "auth": "libs/auth",
    "availability": "apps/availability",
    "books": "apps/books",
    "common": "libs/common",
    "config": "libs/config",
    "database-storage": "libs/database-storage",
    "domain": "libs/domain",
    "domain-testing": "libs/domain-testing",
    "dto": "libs/dto",
    "dto-nest": "libs/dto-nest",
    "dto-testing": "libs/dto-testing",
    "filters": "libs/filters",
    "microservices": "libs/microservices",
    "reservations": "apps/reservations",
    "users": "apps/users",
    "validators": "libs/validators"
  }
}
